{
	"population": {
		"sphere": [
			{
				"_id": "ga-0-1",
				"algorithm": "ga",
				"optimizer": "Minimize",
				"iterations": 201,
				"size": 100,
				"fitness": "sphere",
				"population": [
					[
						0,
						0
					],
					[
						0.3768053421213061,
						0.3768053421213061
					],
					[
						0,
						0
					],
					[
						0.023951362863794755,
						0.023951362863794755
					],
					[
						0,
						0
					],
					[
						0,
						0
					],
					[
						-0.17880082913904863,
						-0.17880082913904863
					],
					[
						0,
						0
					],
					[
						0.0590320097456582,
						0.0590320097456582
					],
					[
						0,
						0
					],
					[
						0,
						0
					],
					[
						0,
						0
					],
					[
						0.15739790640387166,
						0.15739790640387166
					],
					[
						0,
						0
					],
					[
						0,
						0
					],
					[
						0,
						0
					],
					[
						0.04355692632292939,
						0.04355692632292939
					],
					[
						0,
						0
					],
					[
						0,
						0
					],
					[
						0,
						0
					],
					[
						0,
						0
					],
					[
						0.34532922992808707,
						0.34532922992808707
					],
					[
						0,
						0
					],
					[
						0,
						0
					],
					[
						0,
						0
					],
					[
						0,
						0
					],
					[
						0,
						0
					],
					[
						0,
						0
					],
					[
						0,
						0
					],
					[
						0,
						0
					],
					[
						0,
						0
					],
					[
						0,
						0
					],
					[
						-0.04382313321598592,
						-0.04382313321598592
					],
					[
						0.17542447630207872,
						0.17542447630207872
					],
					[
						0,
						0
					],
					[
						0,
						0
					],
					[
						-0.0116453868126964,
						-0.0116453868126964
					],
					[
						0,
						0
					],
					[
						0,
						0
					],
					[
						0,
						0
					],
					[
						0,
						0
					],
					[
						0,
						0
					],
					[
						-0.20574392954242227,
						-0.20574392954242227
					],
					[
						0,
						0
					],
					[
						0,
						0
					],
					[
						0,
						0
					],
					[
						0,
						0
					],
					[
						0,
						0
					],
					[
						0,
						0
					],
					[
						-0.2849697365889028,
						-0.2849697365889028
					],
					[
						0,
						0
					],
					[
						-0.12171654860790451,
						-0.12171654860790451
					],
					[
						-0.10558591607220517,
						-0.10558591607220517
					],
					[
						0,
						0
					],
					[
						0.001418825957799741,
						0.001418825957799741
					],
					[
						0,
						0
					],
					[
						0.22906002106995224,
						0.22906002106995224
					],
					[
						0,
						0
					],
					[
						0,
						0
					],
					[
						-0.3064149822660874,
						-0.3064149822660874
					],
					[
						0,
						0
					],
					[
						0,
						0
					],
					[
						0,
						0
					],
					[
						-0.2748332620837311,
						-0.2748332620837311
					],
					[
						-0.0030344893338323815,
						-0.0030344893338323815
					],
					[
						0.001880591275269273,
						0.001880591275269273
					],
					[
						-0.033820410605514,
						-0.033820410605514
					],
					[
						0.01155333596250177,
						0.01155333596250177
					],
					[
						0,
						0
					],
					[
						0,
						0
					],
					[
						0,
						0
					],
					[
						0,
						0
					],
					[
						0,
						0
					],
					[
						0,
						0
					],
					[
						0,
						0
					],
					[
						0,
						0
					],
					[
						0,
						0
					],
					[
						-0.17092057763790433,
						-0.17092057763790433
					],
					[
						0,
						0
					],
					[
						0,
						0
					],
					[
						0,
						0
					],
					[
						0,
						0
					],
					[
						1.2163921819372334,
						1.2163921819372334
					],
					[
						0,
						0
					],
					[
						0,
						0
					],
					[
						0,
						0
					],
					[
						0.11928227985834884,
						0.11928227985834884
					],
					[
						-0.36436275967722825,
						-0.36436275967722825
					],
					[
						0,
						0
					],
					[
						-0.2256340601486786,
						-0.2256340601486786
					],
					[
						0,
						0
					],
					[
						0,
						0
					],
					[
						0,
						0
					],
					[
						0,
						0
					],
					[
						0,
						0
					],
					[
						0,
						0
					],
					[
						-0.03878850598017408,
						-0.03878850598017408
					],
					[
						0,
						0
					],
					[
						0.8984683523516663,
						0.8984683523516663
					],
					[
						0,
						0
					]
				],
				"mutation": "Tournament3",
				"crossover": "Tournament3",
				"crossoverPer": 0.6,
				"mutationPer": 0.2,
				"crossoverFunc": "splittingPointUniform",
				"mutationFunc": "gaussian",
				"ip": "192.168.1.212",
				"best": 0
			},
			{
				"_id": "pso-0-2",
				"algorithm": "pso",
				"optimizer": "Minimize",
				"iterations": 201,
				"size": 100,
				"fitness": "sphere",
				"population": [
					[
						0,
						0
					],
					[
						0.41214242871961126,
						0.4121424179720781
					],
					[
						0,
						0
					],
					[
						0.023951362863794755,
						0.023951362863794755
					],
					[
						0,
						0
					],
					[
						0.0003946898790113144,
						0
					],
					[
						-0.17096409165459228,
						-0.17096409165459228
					],
					[
						0,
						0
					],
					[
						5.1925077577878525e-12,
						-1.0742340648651207e-8
					],
					[
						0,
						0
					],
					[
						0,
						0
					],
					[
						0,
						0
					],
					[
						0,
						0
					],
					[
						-0.06923599098118638,
						-0.17794704438914888
					],
					[
						0,
						0
					],
					[
						0,
						0
					],
					[
						0.04355692632292939,
						0.04355692632292939
					],
					[
						0,
						0
					],
					[
						0,
						0
					],
					[
						0,
						0
					],
					[
						0,
						0
					],
					[
						0,
						0
					],
					[
						0,
						0
					],
					[
						0,
						0
					],
					[
						0,
						0
					],
					[
						0,
						0
					],
					[
						0,
						0
					],
					[
						0,
						0
					],
					[
						0,
						0
					],
					[
						1.4167188758338811,
						1.4167188758338811
					],
					[
						0,
						0
					],
					[
						0,
						0
					],
					[
						-0.04382313321598592,
						-0.04382313321598592
					],
					[
						0,
						0
					],
					[
						0,
						0
					],
					[
						0,
						0
					],
					[
						0,
						0
					],
					[
						0,
						0
					],
					[
						0,
						0
					],
					[
						0,
						0
					],
					[
						0,
						0
					],
					[
						0,
						0
					],
					[
						0,
						0
					],
					[
						-0.0448008034736298,
						-0.2124168406812963
					],
					[
						0.07779516876903966,
						0.07779516876903966
					],
					[
						0,
						0
					],
					[
						0,
						0
					],
					[
						0,
						0
					],
					[
						0,
						0
					],
					[
						-0.2849697365889028,
						-0.2849697365889028
					],
					[
						0,
						0
					],
					[
						0,
						0
					],
					[
						0,
						0
					],
					[
						0,
						0
					],
					[
						0.001418825957799741,
						0.001418825957799741
					],
					[
						0,
						0
					],
					[
						0,
						0
					],
					[
						0,
						0
					],
					[
						0,
						0
					],
					[
						-0.24271728784418378,
						-0.24271728784418378
					],
					[
						0,
						0
					],
					[
						0,
						0
					],
					[
						0,
						0
					],
					[
						-0.2748332620837311,
						-0.2748332620837311
					],
					[
						0,
						0
					],
					[
						0.001806469394789405,
						0.001806469394789405
					],
					[
						0,
						0
					],
					[
						0.0285905262539329,
						0.0285905262539329
					],
					[
						0,
						0
					],
					[
						0,
						0
					],
					[
						0,
						0
					],
					[
						1.5721831784357743,
						1.5721831784357743
					],
					[
						0,
						0
					],
					[
						0,
						0
					],
					[
						0,
						0
					],
					[
						0,
						0
					],
					[
						0,
						0
					],
					[
						0,
						0
					],
					[
						0,
						0
					],
					[
						0,
						0
					],
					[
						0,
						0
					],
					[
						0,
						0
					],
					[
						1.2163921819372334,
						1.2163921819372334
					],
					[
						5.1925077577878525e-12,
						-1.0742340648651207e-8
					],
					[
						0,
						0
					],
					[
						0,
						0
					],
					[
						0.11928227985834884,
						0.11928227985834884
					],
					[
						-0.36436275967722825,
						-0.36436275967722825
					],
					[
						0,
						0
					],
					[
						0.12344093978317824,
						0.12344093978317824
					],
					[
						-0.0007257993997736946,
						-0.000725810147306851
					],
					[
						0,
						0
					],
					[
						0.053668672556815386,
						0.053668672556815386
					],
					[
						0,
						0
					],
					[
						0,
						0
					],
					[
						0,
						0
					],
					[
						-0.03878850598017408,
						-0.03878850598017408
					],
					[
						0.6906983418307879,
						0.07261081326403757
					],
					[
						0.8984683523516663,
						0.8984683523516663
					],
					[
						0,
						0
					]
				],
				"socialFactor": 2.05,
				"individualFactor": 2.05,
				"inertiaFactor": 1,
				"ip": "192.168.1.212",
				"best": 0
			},
			{
				"_id": "ga-0-3",
				"algorithm": "ga",
				"optimizer": "Minimize",
				"iterations": 201,
				"size": 100,
				"fitness": "sphere",
				"population": [
					[
						0,
						0
					],
					[
						0,
						0
					],
					[
						0,
						0
					],
					[
						0,
						0
					],
					[
						0,
						0
					],
					[
						0,
						0
					],
					[
						-0.078968855087307,
						-0.078968855087307
					],
					[
						0,
						0
					],
					[
						0,
						0
					],
					[
						0,
						0
					],
					[
						0,
						0
					],
					[
						0,
						0
					],
					[
						0,
						0
					],
					[
						0,
						0
					],
					[
						0,
						0
					],
					[
						0,
						0
					],
					[
						0.032806571288909445,
						0.032806571288909445
					],
					[
						0,
						0
					],
					[
						0.17414408040882137,
						0.17414408040882137
					],
					[
						0,
						0
					],
					[
						0,
						0
					],
					[
						0,
						0
					],
					[
						0,
						0
					],
					[
						0,
						0
					],
					[
						0,
						0
					],
					[
						0,
						0
					],
					[
						0.04415703039864953,
						0.04415703039864953
					],
					[
						0,
						0
					],
					[
						0,
						0
					],
					[
						0,
						0
					],
					[
						0,
						0
					],
					[
						0.028258153608521838,
						0.028258153608521838
					],
					[
						-0.0555560485852384,
						-0.0555560485852384
					],
					[
						0,
						0
					],
					[
						0,
						0
					],
					[
						0,
						0
					],
					[
						-0.02720623150426098,
						-0.02720623150426098
					],
					[
						0,
						0
					],
					[
						0.021888475236346273,
						0.021888475236346273
					],
					[
						0,
						0
					],
					[
						0.0028389507881164213,
						0.0028389507881164213
					],
					[
						0,
						0
					],
					[
						-0.04210869894372974,
						-0.04210869894372974
					],
					[
						0,
						0
					],
					[
						0,
						0
					],
					[
						0,
						0
					],
					[
						-0.003346550083824876,
						-0.003346550083824876
					],
					[
						0,
						0
					],
					[
						0,
						0
					],
					[
						0,
						0
					],
					[
						-0.01180877721373803,
						-0.01180877721373803
					],
					[
						0,
						0
					],
					[
						0,
						0
					],
					[
						0,
						0
					],
					[
						0,
						0
					],
					[
						0,
						0
					],
					[
						0,
						0
					],
					[
						0,
						0
					],
					[
						0,
						0
					],
					[
						0.48246812909754855,
						0.48246812909754855
					],
					[
						0,
						0
					],
					[
						0,
						0
					],
					[
						-0.7259283910046928,
						-0.7259283910046928
					],
					[
						0,
						0
					],
					[
						0.05253930790717878,
						0.05253930790717878
					],
					[
						0.002834490780252222,
						0.002834490780252222
					],
					[
						0,
						0
					],
					[
						-0.044889169017448265,
						-0.044889169017448265
					],
					[
						-0.3169720661553454,
						-0.3169720661553454
					],
					[
						0,
						0
					],
					[
						0.031086908334561875,
						0.031086908334561875
					],
					[
						0,
						0
					],
					[
						1.2581508987161885,
						1.2581508987161885
					],
					[
						0.0846677785041772,
						0.0846677785041772
					],
					[
						0,
						0
					],
					[
						0,
						0
					],
					[
						0,
						0
					],
					[
						0,
						0
					],
					[
						0,
						0
					],
					[
						0,
						0
					],
					[
						0.0012431492309207812,
						0.0012431492309207812
					],
					[
						0,
						0
					],
					[
						0.001884624898368735,
						0.001884624898368735
					],
					[
						-0.12342826593317925,
						-0.12342826593317925
					],
					[
						0,
						0
					],
					[
						0,
						0
					],
					[
						-0.011446028904108271,
						-0.011446028904108271
					],
					[
						0,
						0
					],
					[
						0,
						0
					],
					[
						0,
						0
					],
					[
						0.12054316125728883,
						0.12054316125728883
					],
					[
						0,
						0
					],
					[
						0,
						0
					],
					[
						0,
						0
					],
					[
						0,
						0
					],
					[
						0,
						0
					],
					[
						0,
						0
					],
					[
						-0.13390935318907982,
						-0.13390935318907982
					],
					[
						-0.010641926455463338,
						-0.010641926455463338
					],
					[
						0,
						0
					]
				],
				"mutation": "Tournament3",
				"crossover": "Tournament3",
				"crossoverPer": 0.6,
				"mutationPer": 0.2,
				"crossoverFunc": "splittingPointUniform",
				"mutationFunc": "gaussian",
				"ip": "192.168.1.212",
				"best": 0
			},
			{
				"_id": "pso-0-4",
				"algorithm": "pso",
				"optimizer": "Minimize",
				"iterations": 201,
				"size": 100,
				"fitness": "sphere",
				"population": [
					[
						0,
						0
					],
					[
						0.06863004738080998,
						0.06863004738080998
					],
					[
						0,
						0
					],
					[
						0.537976503433141,
						0.537976503433141
					],
					[
						0,
						0
					],
					[
						0,
						0
					],
					[
						0,
						0
					],
					[
						0,
						0
					],
					[
						-0.25584891729507414,
						-0.25584891729507414
					],
					[
						0,
						0
					],
					[
						0,
						0
					],
					[
						0,
						0
					],
					[
						0,
						0
					],
					[
						0,
						0
					],
					[
						-0.02932113268846848,
						-0.02932113268846848
					],
					[
						-0.4849034244649538,
						-0.4849034244649538
					],
					[
						0,
						0
					],
					[
						0,
						0
					],
					[
						0,
						0
					],
					[
						0,
						0
					],
					[
						-1.4644533637930266,
						1.9581770613926845
					],
					[
						0,
						0
					],
					[
						0.21560848031132643,
						0.21560848031132643
					],
					[
						0,
						0
					],
					[
						0,
						0
					],
					[
						0,
						0
					],
					[
						0,
						0
					],
					[
						0,
						0
					],
					[
						0,
						0
					],
					[
						-0.18904791947190258,
						-2.6977965339298677
					],
					[
						-0.7343634503034008,
						-0.7343634503034008
					],
					[
						0,
						0
					],
					[
						0,
						0
					],
					[
						0,
						0
					],
					[
						0,
						0
					],
					[
						0.6305690584466932,
						-0.23753469135801453
					],
					[
						0,
						0
					],
					[
						0,
						0
					],
					[
						-0.11041084311970135,
						-0.11041084311970135
					],
					[
						0,
						0
					],
					[
						0,
						0
					],
					[
						0,
						0
					],
					[
						1.49021854986107,
						-2.5037589751704536
					],
					[
						0.15935290404003344,
						0.15935290404003344
					],
					[
						0,
						0
					],
					[
						0,
						0
					],
					[
						0,
						0
					],
					[
						0,
						0
					],
					[
						0.6349939712546311,
						2.1175126507492554
					],
					[
						0.07875017187661451,
						0.07875017187661451
					],
					[
						0,
						0
					],
					[
						0,
						0
					],
					[
						0,
						0
					],
					[
						0,
						0
					],
					[
						0,
						0
					],
					[
						0,
						0
					],
					[
						-1.6745557338597932,
						-0.6192321841254724
					],
					[
						0.10970728652976369,
						3.1304776410000192
					],
					[
						0,
						0
					],
					[
						-0.15669039638373966,
						-0.15669039638373966
					],
					[
						0,
						0
					],
					[
						0,
						0
					],
					[
						0,
						0
					],
					[
						0,
						0
					],
					[
						0,
						0
					],
					[
						0,
						0
					],
					[
						0,
						0
					],
					[
						-1.4135155970099929,
						0.17065284655831203
					],
					[
						0,
						0
					],
					[
						0,
						0
					],
					[
						0,
						0
					],
					[
						2.616185645580464,
						0.31498766602782347
					],
					[
						0,
						0
					],
					[
						-0.06586703497301635,
						-0.06586703497301635
					],
					[
						0,
						0
					],
					[
						0,
						0
					],
					[
						0,
						0
					],
					[
						0.04144839380011087,
						0.04144839380011087
					],
					[
						0,
						0
					],
					[
						0,
						-5.12
					],
					[
						0,
						0
					],
					[
						0,
						0
					],
					[
						0,
						0
					],
					[
						0,
						0
					],
					[
						0,
						0
					],
					[
						0,
						0
					],
					[
						0.6010270417691321,
						0.9666306094174364
					],
					[
						0,
						0
					],
					[
						0.0027109182575140636,
						0.0027109182575140636
					],
					[
						0,
						0
					],
					[
						0,
						0
					],
					[
						0.20714202145654986,
						0
					],
					[
						0,
						0
					],
					[
						0,
						0
					],
					[
						0,
						0
					],
					[
						0.37589825278713135,
						0.37589825278713135
					],
					[
						0,
						0
					],
					[
						-0.06488626315208228,
						-0.06488626315208228
					],
					[
						0.4514909716460973,
						0.4514909716460973
					],
					[
						0,
						0
					]
				],
				"socialFactor": 2.05,
				"individualFactor": 2.05,
				"inertiaFactor": 1,
				"ip": "192.168.1.212",
				"best": 0
			},
			{
				"_id": "ga-0-5",
				"algorithm": "ga",
				"optimizer": "Minimize",
				"iterations": 201,
				"size": 100,
				"fitness": "sphere",
				"population": [
					[
						0,
						0
					],
					[
						-0.6908490318986186,
						-0.6908490318986186
					],
					[
						0,
						0
					],
					[
						0,
						0
					],
					[
						0,
						0
					],
					[
						-0.08422485333747423,
						-0.08422485333747423
					],
					[
						0,
						0
					],
					[
						0,
						0
					],
					[
						0,
						0
					],
					[
						0,
						0
					],
					[
						0,
						0
					],
					[
						0,
						0
					],
					[
						0,
						0
					],
					[
						-0.2498796500991128,
						-0.2498796500991128
					],
					[
						0,
						0
					],
					[
						0,
						0
					],
					[
						0,
						0
					],
					[
						0.10691635587952732,
						0.10691635587952732
					],
					[
						0,
						0
					],
					[
						0,
						0
					],
					[
						0,
						0
					],
					[
						0,
						0
					],
					[
						-0.3615933351492209,
						-0.3615933351492209
					],
					[
						0,
						0
					],
					[
						0,
						0
					],
					[
						-0.13962137145547895,
						-0.13962137145547895
					],
					[
						0,
						0
					],
					[
						0,
						0
					],
					[
						0,
						0
					],
					[
						0,
						0
					],
					[
						0,
						0
					],
					[
						0,
						0
					],
					[
						0.16898491674936378,
						0.16898491674936378
					],
					[
						0,
						0
					],
					[
						0,
						0
					],
					[
						0.03838381013739912,
						0.03838381013739912
					],
					[
						0,
						0
					],
					[
						0,
						0
					],
					[
						0,
						0
					],
					[
						0,
						0
					],
					[
						0,
						0
					],
					[
						0,
						0
					],
					[
						0,
						0
					],
					[
						-1.1946149547110738,
						-1.1946149547110738
					],
					[
						0.3121030247503125,
						0.3121030247503125
					],
					[
						0,
						0
					],
					[
						0,
						0
					],
					[
						0,
						0
					],
					[
						0,
						0
					],
					[
						0,
						0
					],
					[
						0,
						0
					],
					[
						0,
						0
					],
					[
						0,
						0
					],
					[
						0.020618689177716917,
						0.020618689177716917
					],
					[
						0,
						0
					],
					[
						0.5737408167625,
						0.5737408167625
					],
					[
						0,
						0
					],
					[
						0,
						0
					],
					[
						0,
						0
					],
					[
						0,
						0
					],
					[
						0,
						0
					],
					[
						0,
						0
					],
					[
						0,
						0
					],
					[
						0,
						0
					],
					[
						0,
						0
					],
					[
						0,
						0
					],
					[
						0,
						0
					],
					[
						0,
						0
					],
					[
						-0.1821940943079316,
						-0.1821940943079316
					],
					[
						0,
						0
					],
					[
						0,
						0
					],
					[
						0,
						0
					],
					[
						-0.3196163534057416,
						-0.3196163534057416
					],
					[
						0,
						0
					],
					[
						0,
						0
					],
					[
						0,
						0
					],
					[
						0,
						0
					],
					[
						0,
						0
					],
					[
						0,
						0
					],
					[
						0,
						0
					],
					[
						0.00581495224837868,
						0.00581495224837868
					],
					[
						0,
						0
					],
					[
						0,
						0
					],
					[
						0,
						0
					],
					[
						0,
						0
					],
					[
						0,
						0
					],
					[
						0,
						0
					],
					[
						0,
						0
					],
					[
						0.020523223353147102,
						0.020523223353147102
					],
					[
						0,
						0
					],
					[
						0,
						0
					],
					[
						0,
						0
					],
					[
						0,
						0
					],
					[
						0,
						0
					],
					[
						0,
						0
					],
					[
						0,
						0
					],
					[
						0,
						0
					],
					[
						0.03344782342622948,
						0.03344782342622948
					],
					[
						0,
						0
					],
					[
						0,
						0
					]
				],
				"mutation": "Tournament3",
				"crossover": "Tournament3",
				"crossoverPer": 0.6,
				"mutationPer": 0.2,
				"crossoverFunc": "splittingPointUniform",
				"mutationFunc": "gaussian",
				"ip": "192.168.1.212",
				"best": 0
			},
			{
				"_id": "pso-0-6",
				"algorithm": "pso",
				"optimizer": "Minimize",
				"iterations": 201,
				"size": 100,
				"fitness": "sphere",
				"population": [
					[
						0,
						0
					],
					[
						0,
						0
					],
					[
						0,
						0
					],
					[
						0.18521851933647734,
						0.18521851933647734
					],
					[
						0,
						0
					],
					[
						-0.2462332522033154,
						-0.2462332522033154
					],
					[
						0,
						0
					],
					[
						0,
						0
					],
					[
						0,
						0
					],
					[
						3.4563022599911193,
						0
					],
					[
						0,
						0
					],
					[
						0,
						0
					],
					[
						0.09954907208749875,
						0.09954907208749875
					],
					[
						0,
						0
					],
					[
						0,
						0
					],
					[
						-0.15484992581472418,
						-0.15484992581472418
					],
					[
						0,
						0
					],
					[
						0,
						0
					],
					[
						0,
						0
					],
					[
						1.2383300337044276,
						-2.3199547873987494
					],
					[
						0,
						0
					],
					[
						0,
						0
					],
					[
						0,
						0
					],
					[
						0,
						1.040757511543417
					],
					[
						0,
						0
					],
					[
						0,
						0
					],
					[
						0,
						0
					],
					[
						0,
						0
					],
					[
						0,
						0
					],
					[
						-0.29538832817128613,
						1.1456065225392034
					],
					[
						0,
						0
					],
					[
						0,
						0
					],
					[
						0,
						0
					],
					[
						0,
						0
					],
					[
						0,
						0
					],
					[
						0,
						0
					],
					[
						0,
						0
					],
					[
						0,
						0
					],
					[
						0,
						0
					],
					[
						0,
						0
					],
					[
						0,
						0
					],
					[
						0,
						0
					],
					[
						0,
						0
					],
					[
						0,
						0
					],
					[
						0,
						0
					],
					[
						0,
						0
					],
					[
						0,
						0
					],
					[
						0,
						0
					],
					[
						0,
						0
					],
					[
						0,
						0
					],
					[
						1.703244422664595,
						-2.6949116754664315
					],
					[
						0,
						0
					],
					[
						0,
						0
					],
					[
						0,
						0
					],
					[
						0,
						0
					],
					[
						0,
						0
					],
					[
						0.584708891436612,
						0.584708891436612
					],
					[
						0,
						0
					],
					[
						0.034483057373895475,
						0.034483057373895475
					],
					[
						0.2021689515670459,
						0.2021689515670459
					],
					[
						0,
						0
					],
					[
						0,
						0
					],
					[
						0,
						0
					],
					[
						0,
						0
					],
					[
						0,
						0
					],
					[
						0,
						0
					],
					[
						0,
						0
					],
					[
						0,
						0
					],
					[
						-1.1041889920555104,
						2.0576297220835453
					],
					[
						0,
						0
					],
					[
						0,
						0
					],
					[
						0.23042899825320556,
						0.22760387946833824
					],
					[
						0,
						0
					],
					[
						0,
						0
					],
					[
						0,
						0
					],
					[
						0,
						0
					],
					[
						0,
						0
					],
					[
						0,
						0
					],
					[
						0,
						0
					],
					[
						0,
						0
					],
					[
						0.6631330567333771,
						0.6631330567333771
					],
					[
						0,
						0
					],
					[
						0,
						0
					],
					[
						0,
						0
					],
					[
						0.021607683681657778,
						0.021607683681657778
					],
					[
						-0.5102493746953847,
						-0.5102493746953847
					],
					[
						0.015086590671836845,
						0.015086590671836845
					],
					[
						0,
						-0.07217395809644467
					],
					[
						0.8714430743564776,
						0.3739140315388716
					],
					[
						0,
						0
					],
					[
						-0.11026782253487816,
						-0.11026782253487816
					],
					[
						0,
						0
					],
					[
						0,
						0
					],
					[
						0,
						0
					],
					[
						0,
						0
					],
					[
						-0.007332698649186491,
						-0.007332698649186491
					],
					[
						0,
						0
					],
					[
						0,
						0
					],
					[
						0,
						0
					],
					[
						0,
						0
					]
				],
				"socialFactor": 2.05,
				"individualFactor": 2.05,
				"inertiaFactor": 1,
				"ip": "192.168.1.212",
				"best": 0
			},
			{
				"_id": "pso-0-10",
				"algorithm": "pso",
				"optimizer": "Minimize",
				"iterations": 201,
				"size": 100,
				"fitness": "sphere",
				"population": [
					[
						0,
						0
					],
					[
						0,
						0
					],
					[
						0,
						0
					],
					[
						0,
						0
					],
					[
						-1.490056924479997,
						0.8959498472747489
					],
					[
						0,
						0
					],
					[
						0,
						0
					],
					[
						0,
						0
					],
					[
						0,
						0
					],
					[
						0,
						0
					],
					[
						0,
						0
					],
					[
						0.10076923741351926,
						0.10076923741351926
					],
					[
						0,
						0
					],
					[
						0,
						0
					],
					[
						-0.00647342058528312,
						-0.00647342058528312
					],
					[
						0.09913389251273563,
						0.09913389251273563
					],
					[
						0,
						0
					],
					[
						0,
						0
					],
					[
						0,
						0
					],
					[
						0,
						0
					],
					[
						0,
						0
					],
					[
						0,
						0
					],
					[
						0,
						0
					],
					[
						-1.0052328575696432,
						1.243807214393859
					],
					[
						0,
						0
					],
					[
						0,
						0
					],
					[
						0,
						0
					],
					[
						0,
						0
					],
					[
						0.4088376453540028,
						-0.9824216843950997
					],
					[
						0,
						0
					],
					[
						0,
						0
					],
					[
						0,
						0
					],
					[
						0,
						-0.0012601107761221497
					],
					[
						0.01401999613822141,
						0.01401999613822141
					],
					[
						-0.0031097287907782627,
						-0.0031097287907782627
					],
					[
						0,
						0
					],
					[
						0,
						0
					],
					[
						0,
						0
					],
					[
						0,
						0
					],
					[
						0.03778138653155296,
						0.03778138653155296
					],
					[
						0,
						0
					],
					[
						0,
						0
					],
					[
						0,
						0
					],
					[
						0,
						0
					],
					[
						0,
						0
					],
					[
						0,
						0
					],
					[
						0,
						0
					],
					[
						0.2155815297299693,
						0.2155815297299693
					],
					[
						0,
						0
					],
					[
						0,
						0
					],
					[
						0,
						0
					],
					[
						0,
						0
					],
					[
						0,
						0
					],
					[
						0,
						0
					],
					[
						-0.03823594551766707,
						2.132853591959685
					],
					[
						0,
						0
					],
					[
						0,
						0
					],
					[
						0.06506920136547975,
						0.06506920136547975
					],
					[
						0,
						0
					],
					[
						1.7700605902562891,
						-1.96432934788489
					],
					[
						0,
						0
					],
					[
						0,
						0
					],
					[
						0,
						0
					],
					[
						0,
						0
					],
					[
						0,
						0
					],
					[
						0,
						0
					],
					[
						1.8657148957952492,
						-2.8780034310305656
					],
					[
						0,
						0
					],
					[
						0,
						0
					],
					[
						-0.3227793306394144,
						-0.3227793306394144
					],
					[
						0,
						0
					],
					[
						0,
						0
					],
					[
						0,
						0.00832503154755107
					],
					[
						-0.08977979219352439,
						-0.09394230796729992
					],
					[
						0,
						0
					],
					[
						0,
						0
					],
					[
						-0.08865061207950696,
						-0.08865061207950696
					],
					[
						-0.20649533124646285,
						-0.20649533124646285
					],
					[
						0,
						0
					],
					[
						0,
						0
					],
					[
						0,
						0
					],
					[
						0,
						0
					],
					[
						0.003304734181222162,
						0.003304734181222162
					],
					[
						0,
						0
					],
					[
						0,
						0
					],
					[
						0,
						0
					],
					[
						0,
						0
					],
					[
						0.40520128283104806,
						2.255840596109039
					],
					[
						-0.22818247262464894,
						-0.22818247262464894
					],
					[
						0,
						0
					],
					[
						0,
						0
					],
					[
						0,
						0
					],
					[
						0,
						0
					],
					[
						-1.7937996635916553,
						-1.7937996635916553
					],
					[
						0,
						0
					],
					[
						0,
						0
					],
					[
						0,
						0
					],
					[
						0,
						0
					],
					[
						0,
						0
					],
					[
						0.06237274813703947,
						0.06237274813703947
					]
				],
				"socialFactor": 2.05,
				"individualFactor": 2.05,
				"inertiaFactor": 1,
				"ip": "192.168.1.212",
				"best": 0
			},
			{
				"_id": "ga-0-9",
				"algorithm": "ga",
				"optimizer": "Minimize",
				"iterations": 201,
				"size": 100,
				"fitness": "sphere",
				"population": [
					[
						0,
						0
					],
					[
						0,
						0
					],
					[
						0,
						0
					],
					[
						-0.35793300486583796,
						-0.35793300486583796
					],
					[
						0,
						0
					],
					[
						0,
						0
					],
					[
						0,
						0
					],
					[
						-0.006474518257682178,
						-0.006474518257682178
					],
					[
						0,
						0
					],
					[
						0,
						0
					],
					[
						-0.11685672282078083,
						-0.11685672282078083
					],
					[
						0,
						0
					],
					[
						0,
						0
					],
					[
						0,
						0
					],
					[
						0,
						0
					],
					[
						0,
						0
					],
					[
						0,
						0
					],
					[
						0,
						0
					],
					[
						0.003392289270633395,
						0.003392289270633395
					],
					[
						0,
						0
					],
					[
						0,
						0
					],
					[
						-0.8111554607488347,
						-0.8111554607488347
					],
					[
						0,
						0
					],
					[
						0,
						0
					],
					[
						0,
						0
					],
					[
						0.0013332711395785926,
						0.0013332711395785926
					],
					[
						0,
						0
					],
					[
						0,
						0
					],
					[
						0,
						0
					],
					[
						0,
						0
					],
					[
						0,
						0
					],
					[
						0,
						0
					],
					[
						0.4342906844840238,
						0.4342906844840238
					],
					[
						0,
						0
					],
					[
						0,
						0
					],
					[
						0,
						0
					],
					[
						0,
						0
					],
					[
						0,
						0
					],
					[
						0,
						0
					],
					[
						0,
						0
					],
					[
						0,
						0
					],
					[
						0,
						0
					],
					[
						0,
						0
					],
					[
						0,
						0
					],
					[
						0,
						0
					],
					[
						0,
						0
					],
					[
						0,
						0
					],
					[
						0,
						0
					],
					[
						-0.19977581417269047,
						-0.19977581417269047
					],
					[
						0,
						0
					],
					[
						0,
						0
					],
					[
						0,
						0
					],
					[
						0,
						0
					],
					[
						0,
						0
					],
					[
						0.01868315199074244,
						0.01868315199074244
					],
					[
						0.017311391695924827,
						0.017311391695924827
					],
					[
						0.11313782188827877,
						0.11313782188827877
					],
					[
						0,
						0
					],
					[
						0.10238807424257694,
						0.10238807424257694
					],
					[
						0,
						0
					],
					[
						0,
						0
					],
					[
						0,
						0
					],
					[
						0,
						0
					],
					[
						0,
						0
					],
					[
						0,
						0
					],
					[
						0,
						0
					],
					[
						0.09105861346373882,
						0.09105861346373882
					],
					[
						0,
						0
					],
					[
						0,
						0
					],
					[
						0.042911984068994206,
						0.042911984068994206
					],
					[
						0,
						0
					],
					[
						0,
						0
					],
					[
						0,
						0
					],
					[
						0,
						0
					],
					[
						0,
						0
					],
					[
						0,
						0
					],
					[
						0,
						0
					],
					[
						0,
						0
					],
					[
						0,
						0
					],
					[
						0,
						0
					],
					[
						0,
						0
					],
					[
						0,
						0
					],
					[
						0,
						0
					],
					[
						0,
						0
					],
					[
						0,
						0
					],
					[
						-0.15945428457878227,
						-0.15945428457878227
					],
					[
						0,
						0
					],
					[
						0,
						0
					],
					[
						0,
						0
					],
					[
						1.1020836788307766,
						1.1020836788307766
					],
					[
						0,
						0
					],
					[
						0,
						0
					],
					[
						0,
						0
					],
					[
						0,
						0
					],
					[
						0,
						0
					],
					[
						0,
						0
					],
					[
						0,
						0
					],
					[
						0,
						0
					],
					[
						0,
						0
					],
					[
						0,
						0
					]
				],
				"mutation": "Tournament3",
				"crossover": "Tournament3",
				"crossoverPer": 0.6,
				"mutationPer": 0.2,
				"crossoverFunc": "splittingPointUniform",
				"mutationFunc": "gaussian",
				"ip": "192.168.1.212",
				"best": 0
			},
			{
				"_id": "ga-0-7",
				"algorithm": "ga",
				"optimizer": "Minimize",
				"iterations": 201,
				"size": 100,
				"fitness": "sphere",
				"population": [
					[
						0,
						0
					],
					[
						0.3557664376546135,
						0.3557664376546135
					],
					[
						0,
						0
					],
					[
						0,
						0
					],
					[
						-0.05372185516099503,
						-0.05372185516099503
					],
					[
						0,
						0
					],
					[
						-0.317841477234764,
						-0.317841477234764
					],
					[
						0,
						0
					],
					[
						0,
						0
					],
					[
						-0.4657092733980393,
						-0.4657092733980393
					],
					[
						-0.741657678492784,
						-0.741657678492784
					],
					[
						0,
						0
					],
					[
						0,
						0
					],
					[
						0,
						0
					],
					[
						0,
						0
					],
					[
						0,
						0
					],
					[
						0,
						0
					],
					[
						0,
						0
					],
					[
						0,
						0
					],
					[
						0,
						0
					],
					[
						0,
						0
					],
					[
						0,
						0
					],
					[
						0,
						0
					],
					[
						0,
						0
					],
					[
						0,
						0
					],
					[
						0,
						0
					],
					[
						0,
						0
					],
					[
						0,
						0
					],
					[
						0,
						0
					],
					[
						0.12474314345662389,
						0.12474314345662389
					],
					[
						0.7798861457410876,
						0.7798861457410876
					],
					[
						0.2881820249589684,
						0.2881820249589684
					],
					[
						0.0023063864788066776,
						0.0023063864788066776
					],
					[
						0,
						0
					],
					[
						-0.097238358518408,
						-0.097238358518408
					],
					[
						0.574397469185941,
						0.574397469185941
					],
					[
						0,
						0
					],
					[
						0,
						0
					],
					[
						0.0014543155231794406,
						0.0014543155231794406
					],
					[
						0,
						0
					],
					[
						0.2715232490491316,
						0.2715232490491316
					],
					[
						0,
						0
					],
					[
						0,
						0
					],
					[
						0,
						0
					],
					[
						-0.39538989169002586,
						-0.39538989169002586
					],
					[
						-0.23580659528206233,
						-0.23580659528206233
					],
					[
						0,
						0
					],
					[
						0,
						0
					],
					[
						0,
						0
					],
					[
						0,
						0
					],
					[
						0,
						0
					],
					[
						0.009262082916140361,
						0.009262082916140361
					],
					[
						-0.3318904208191897,
						-0.3318904208191897
					],
					[
						-0.033616057206046,
						-0.033616057206046
					],
					[
						0,
						0
					],
					[
						0,
						0
					],
					[
						0,
						0
					],
					[
						0,
						0
					],
					[
						0,
						0
					],
					[
						0,
						0
					],
					[
						0,
						0
					],
					[
						0.02593405538192803,
						0.02593405538192803
					],
					[
						0,
						0
					],
					[
						0,
						0
					],
					[
						0,
						0
					],
					[
						0,
						0
					],
					[
						-0.010582163325558726,
						-0.010582163325558726
					],
					[
						-0.011086508672982458,
						-0.011086508672982458
					],
					[
						0,
						0
					],
					[
						0,
						0
					],
					[
						0,
						0
					],
					[
						-1.2497572968012634,
						-1.2497572968012634
					],
					[
						0,
						0
					],
					[
						0,
						0
					],
					[
						0,
						0
					],
					[
						0,
						0
					],
					[
						0,
						0
					],
					[
						-0.9424578775913552,
						-0.9424578775913552
					],
					[
						0,
						0
					],
					[
						0,
						0
					],
					[
						0,
						0
					],
					[
						0,
						0
					],
					[
						0,
						0
					],
					[
						0,
						0
					],
					[
						0,
						0
					],
					[
						0,
						0
					],
					[
						0.05450846980452252,
						0.05450846980452252
					],
					[
						0.32709259667678015,
						0.32709259667678015
					],
					[
						0.016612335790916154,
						0.016612335790916154
					],
					[
						0,
						0
					],
					[
						0,
						0
					],
					[
						0,
						0
					],
					[
						0,
						0
					],
					[
						-0.22618264185823775,
						-0.22618264185823775
					],
					[
						0,
						0
					],
					[
						0,
						0
					],
					[
						0,
						0
					],
					[
						0,
						0
					],
					[
						0,
						0
					],
					[
						-0.009092288351010109,
						-0.009092288351010109
					]
				],
				"mutation": "Tournament3",
				"crossover": "Tournament3",
				"crossoverPer": 0.6,
				"mutationPer": 0.2,
				"crossoverFunc": "splittingPointUniform",
				"mutationFunc": "gaussian",
				"ip": "192.168.1.212",
				"best": 0
			},
			{
				"_id": "pso-0-8",
				"algorithm": "pso",
				"optimizer": "Minimize",
				"iterations": 201,
				"size": 100,
				"fitness": "sphere",
				"population": [
					[
						0,
						0
					],
					[
						0.3023989423668877,
						0.3023989423668877
					],
					[
						0,
						0
					],
					[
						0,
						0
					],
					[
						-0.2540664412935573,
						-0.2540664412935573
					],
					[
						0,
						0
					],
					[
						0,
						0
					],
					[
						0,
						0
					],
					[
						0,
						0
					],
					[
						0,
						0
					],
					[
						0,
						0
					],
					[
						0.10076923741351926,
						0.10076923741351926
					],
					[
						0,
						0
					],
					[
						0,
						0
					],
					[
						-0.00647342058528312,
						-0.00647342058528312
					],
					[
						0.09913389251273563,
						0.09913389251273563
					],
					[
						0,
						0
					],
					[
						0,
						0
					],
					[
						0,
						0
					],
					[
						0,
						0
					],
					[
						0,
						0
					],
					[
						-0.6889829787887525,
						-0.15374493838085979
					],
					[
						0,
						0
					],
					[
						0,
						0
					],
					[
						0,
						0
					],
					[
						0.07779968066353714,
						0.07779968066353714
					],
					[
						0,
						0
					],
					[
						0,
						0
					],
					[
						0,
						0
					],
					[
						0,
						0
					],
					[
						0,
						0
					],
					[
						0,
						0
					],
					[
						-0.09462779103437059,
						-0.09462779103437059
					],
					[
						0,
						0
					],
					[
						1.3274205694299157,
						0
					],
					[
						0,
						0
					],
					[
						0,
						0
					],
					[
						0,
						0
					],
					[
						0,
						0
					],
					[
						0,
						0
					],
					[
						0,
						0
					],
					[
						0,
						0
					],
					[
						0,
						0
					],
					[
						0,
						0
					],
					[
						0,
						0
					],
					[
						0,
						0
					],
					[
						0.5832630655451874,
						0.5832630655451874
					],
					[
						0.2155815297299693,
						0.2155815297299693
					],
					[
						0,
						0
					],
					[
						0,
						0
					],
					[
						-0.3835940490930847,
						0.5431565803879699
					],
					[
						0,
						-0.013964287300844069
					],
					[
						0,
						0
					],
					[
						0,
						0
					],
					[
						-0.6817301182936553,
						-0.6817301182936553
					],
					[
						0,
						0
					],
					[
						0,
						0
					],
					[
						0.06506920136547975,
						0.06506920136547975
					],
					[
						0,
						0
					],
					[
						0.2021689515670459,
						0.2021689515670459
					],
					[
						0,
						0
					],
					[
						0,
						0
					],
					[
						0,
						0
					],
					[
						0,
						0
					],
					[
						0,
						0
					],
					[
						0,
						0
					],
					[
						0,
						0
					],
					[
						0,
						-1.4957671190771638
					],
					[
						-0.10648815477170664,
						-0.10648815477170664
					],
					[
						0,
						0
					],
					[
						0,
						0
					],
					[
						0,
						0
					],
					[
						0,
						0.00832503154755107
					],
					[
						-0.08977979219352439,
						-0.09394230796729992
					],
					[
						0,
						0
					],
					[
						-0.03564391762853743,
						-0.03564391762853743
					],
					[
						0,
						0
					],
					[
						-0.20649533124646285,
						-0.20649533124646285
					],
					[
						0.027120924032684166,
						0.027120924032684166
					],
					[
						0.0007514898209124004,
						0.0007514898209124004
					],
					[
						0,
						0
					],
					[
						0,
						0
					],
					[
						0.46839806631959247,
						0.46839806631959247
					],
					[
						0.03576668704770355,
						0.03576668704770355
					],
					[
						0,
						0
					],
					[
						0,
						0
					],
					[
						0.015086590671836845,
						0.015086590671836845
					],
					[
						0,
						0
					],
					[
						0,
						0
					],
					[
						0,
						0
					],
					[
						-0.11026782253487816,
						-0.11026782253487816
					],
					[
						0,
						0
					],
					[
						0,
						0
					],
					[
						0,
						0
					],
					[
						0.391212771675971,
						0
					],
					[
						0,
						0
					],
					[
						-1.3514963908188116,
						0.2449096392387018
					],
					[
						0,
						0
					],
					[
						-1.4890245936502855,
						1.4766173858696154
					],
					[
						0.06237274813703947,
						0.06237274813703947
					]
				],
				"socialFactor": 2.05,
				"individualFactor": 2.05,
				"inertiaFactor": 1,
				"ip": "192.168.1.212",
				"best": 0
			}
		],
		"rastrigin": []
	},
	"bestsByIteration": {
		"sphere": [
			{
				"_id": "5cda2c2126aad517ddea5b48",
				"expId": 1557802012993,
				"iteration": 12,
				"best": 0,
				"bestId": "pso-0-2",
				"alg": "pso",
				"fitness": "sphere"
			},
			{
				"_id": "5cda2c2126aad517ddea5b49",
				"expId": 1557802012993,
				"iteration": 14,
				"best": 0,
				"bestId": "pso-0-2",
				"alg": "pso",
				"fitness": "sphere"
			},
			{
				"_id": "5cda2c2126aad517ddea5b4a",
				"expId": 1557802012993,
				"iteration": 16,
				"best": 0,
				"bestId": "pso-0-2",
				"alg": "pso",
				"fitness": "sphere"
			},
			{
				"_id": "5cda2c2126aad517ddea5b4b",
				"expId": 1557802012993,
				"iteration": 18,
				"best": 0,
				"bestId": "pso-0-2",
				"alg": "pso",
				"fitness": "sphere"
			},
			{
				"_id": "5cda2c2226aad517ddea5b4c",
				"expId": 1557802012993,
				"iteration": 20,
				"best": 0,
				"bestId": "ga-0-1",
				"alg": "ga",
				"fitness": "sphere"
			},
			{
				"_id": "5cda2c2226aad517ddea5b4d",
				"expId": 1557802012993,
				"iteration": 22,
				"best": 0,
				"bestId": "ga-0-1",
				"alg": "ga",
				"fitness": "sphere"
			},
			{
				"_id": "5cda2c2226aad517ddea5b4e",
				"expId": 1557802012993,
				"iteration": 24,
				"best": 0,
				"bestId": "ga-0-1",
				"alg": "ga",
				"fitness": "sphere"
			},
			{
				"_id": "5cda2c2226aad517ddea5b4f",
				"expId": 1557802012993,
				"iteration": 26,
				"best": 0,
				"bestId": "ga-0-1",
				"alg": "ga",
				"fitness": "sphere"
			},
			{
				"_id": "5cda2c2226aad517ddea5b50",
				"expId": 1557802012993,
				"iteration": 28,
				"best": 0,
				"bestId": "ga-0-1",
				"alg": "ga",
				"fitness": "sphere"
			},
			{
				"_id": "5cda2c2226aad517ddea5b51",
				"expId": 1557802012993,
				"iteration": 30,
				"best": 0,
				"bestId": "ga-0-1",
				"alg": "ga",
				"fitness": "sphere"
			},
			{
				"_id": "5cda2c2426aad517ddea5b52",
				"expId": 1557802012993,
				"iteration": 34,
				"best": 0,
				"bestId": "ga-0-1",
				"alg": "ga",
				"fitness": "sphere"
			},
			{
				"_id": "5cda2c2426aad517ddea5b53",
				"expId": 1557802012993,
				"iteration": 34,
				"best": 0,
				"bestId": "ga-0-1",
				"alg": "ga",
				"fitness": "sphere"
			},
			{
				"_id": "5cda2c2426aad517ddea5b54",
				"expId": 1557802012993,
				"iteration": 38,
				"best": 0,
				"bestId": "ga-0-1",
				"alg": "ga",
				"fitness": "sphere"
			},
			{
				"_id": "5cda2c2426aad517ddea5b55",
				"expId": 1557802012993,
				"iteration": 38,
				"best": 0,
				"bestId": "ga-0-1",
				"alg": "ga",
				"fitness": "sphere"
			},
			{
				"_id": "5cda2c2426aad517ddea5b56",
				"expId": 1557802012993,
				"iteration": 40,
				"best": 0,
				"bestId": "ga-0-1",
				"alg": "ga",
				"fitness": "sphere"
			},
			{
				"_id": "5cda2c2426aad517ddea5b57",
				"expId": 1557802012993,
				"iteration": 42,
				"best": 0,
				"bestId": "ga-0-1",
				"alg": "ga",
				"fitness": "sphere"
			},
			{
				"_id": "5cda2c2426aad517ddea5b58",
				"expId": 1557802012993,
				"iteration": 44,
				"best": 0,
				"bestId": "ga-0-1",
				"alg": "ga",
				"fitness": "sphere"
			},
			{
				"_id": "5cda2c2426aad517ddea5b59",
				"expId": 1557802012993,
				"iteration": 46,
				"best": 0,
				"bestId": "ga-0-1",
				"alg": "ga",
				"fitness": "sphere"
			},
			{
				"_id": "5cda2c2526aad517ddea5b5a",
				"expId": 1557802012993,
				"iteration": 48,
				"best": 0,
				"bestId": "ga-0-1",
				"alg": "ga",
				"fitness": "sphere"
			},
			{
				"_id": "5cda2c2526aad517ddea5b5b",
				"expId": 1557802012993,
				"iteration": 50,
				"best": 0,
				"bestId": "ga-0-1",
				"alg": "ga",
				"fitness": "sphere"
			},
			{
				"_id": "5cda2c2526aad517ddea5b5c",
				"expId": 1557802012993,
				"iteration": 52,
				"best": 0,
				"bestId": "ga-0-1",
				"alg": "ga",
				"fitness": "sphere"
			},
			{
				"_id": "5cda2c2526aad517ddea5b5d",
				"expId": 1557802012993,
				"iteration": 54,
				"best": 0,
				"bestId": "ga-0-1",
				"alg": "ga",
				"fitness": "sphere"
			},
			{
				"_id": "5cda2c2526aad517ddea5b5e",
				"expId": 1557802012993,
				"iteration": 56,
				"best": 0,
				"bestId": "ga-0-1",
				"alg": "ga",
				"fitness": "sphere"
			},
			{
				"_id": "5cda2c2526aad517ddea5b5f",
				"expId": 1557802012993,
				"iteration": 58,
				"best": 0,
				"bestId": "ga-0-1",
				"alg": "ga",
				"fitness": "sphere"
			},
			{
				"_id": "5cda2c2626aad517ddea5b60",
				"expId": 1557802012993,
				"iteration": 60,
				"best": 0,
				"bestId": "ga-0-1",
				"alg": "ga",
				"fitness": "sphere"
			},
			{
				"_id": "5cda2c2626aad517ddea5b61",
				"expId": 1557802012993,
				"iteration": 62,
				"best": 0,
				"bestId": "ga-0-1",
				"alg": "ga",
				"fitness": "sphere"
			},
			{
				"_id": "5cda2c2626aad517ddea5b62",
				"expId": 1557802012993,
				"iteration": 64,
				"best": 0,
				"bestId": "ga-0-1",
				"alg": "ga",
				"fitness": "sphere"
			},
			{
				"_id": "5cda2c2626aad517ddea5b63",
				"expId": 1557802012993,
				"iteration": 66,
				"best": 0,
				"bestId": "ga-0-1",
				"alg": "ga",
				"fitness": "sphere"
			},
			{
				"_id": "5cda2c2626aad517ddea5b64",
				"expId": 1557802012993,
				"iteration": 68,
				"best": 0,
				"bestId": "ga-0-1",
				"alg": "ga",
				"fitness": "sphere"
			},
			{
				"_id": "5cda2c2626aad517ddea5b65",
				"expId": 1557802012993,
				"iteration": 70,
				"best": 0,
				"bestId": "ga-0-1",
				"alg": "ga",
				"fitness": "sphere"
			},
			{
				"_id": "5cda2c2726aad517ddea5b66",
				"expId": 1557802012993,
				"iteration": 72,
				"best": 0,
				"bestId": "ga-0-1",
				"alg": "ga",
				"fitness": "sphere"
			},
			{
				"_id": "5cda2c2726aad517ddea5b67",
				"expId": 1557802012993,
				"iteration": 74,
				"best": 0,
				"bestId": "ga-0-1",
				"alg": "ga",
				"fitness": "sphere"
			},
			{
				"_id": "5cda2c2726aad517ddea5b68",
				"expId": 1557802012993,
				"iteration": 76,
				"best": 0,
				"bestId": "ga-0-1",
				"alg": "ga",
				"fitness": "sphere"
			},
			{
				"_id": "5cda2c2726aad517ddea5b69",
				"expId": 1557802012993,
				"iteration": 78,
				"best": 0,
				"bestId": "ga-0-1",
				"alg": "ga",
				"fitness": "sphere"
			},
			{
				"_id": "5cda2c2726aad517ddea5b6a",
				"expId": 1557802012993,
				"iteration": 80,
				"best": 0,
				"bestId": "ga-0-1",
				"alg": "ga",
				"fitness": "sphere"
			},
			{
				"_id": "5cda2c2726aad517ddea5b6b",
				"expId": 1557802012993,
				"iteration": 82,
				"best": 0,
				"bestId": "ga-0-1",
				"alg": "ga",
				"fitness": "sphere"
			},
			{
				"_id": "5cda2c2726aad517ddea5b6c",
				"expId": 1557802012993,
				"iteration": 84,
				"best": 0,
				"bestId": "ga-0-1",
				"alg": "ga",
				"fitness": "sphere"
			},
			{
				"_id": "5cda2c2726aad517ddea5b6d",
				"expId": 1557802012993,
				"iteration": 86,
				"best": 0,
				"bestId": "ga-0-1",
				"alg": "ga",
				"fitness": "sphere"
			},
			{
				"_id": "5cda2c2726aad517ddea5b6e",
				"expId": 1557802012993,
				"iteration": 88,
				"best": 0,
				"bestId": "ga-0-1",
				"alg": "ga",
				"fitness": "sphere"
			},
			{
				"_id": "5cda2c2826aad517ddea5b6f",
				"expId": 1557802012993,
				"iteration": 90,
				"best": 0,
				"bestId": "ga-0-1",
				"alg": "ga",
				"fitness": "sphere"
			},
			{
				"_id": "5cda2c2826aad517ddea5b70",
				"expId": 1557802012993,
				"iteration": 94,
				"best": 0,
				"bestId": "ga-0-1",
				"alg": "ga",
				"fitness": "sphere"
			},
			{
				"_id": "5cda2c2826aad517ddea5b71",
				"expId": 1557802012993,
				"iteration": 94,
				"best": 0,
				"bestId": "ga-0-1",
				"alg": "ga",
				"fitness": "sphere"
			},
			{
				"_id": "5cda2c2826aad517ddea5b72",
				"expId": 1557802012993,
				"iteration": 96,
				"best": 0,
				"bestId": "ga-0-1",
				"alg": "ga",
				"fitness": "sphere"
			},
			{
				"_id": "5cda2c2826aad517ddea5b73",
				"expId": 1557802012993,
				"iteration": 98,
				"best": 0,
				"bestId": "ga-0-1",
				"alg": "ga",
				"fitness": "sphere"
			},
			{
				"_id": "5cda2c2826aad517ddea5b74",
				"expId": 1557802012993,
				"iteration": 100,
				"best": 0,
				"bestId": "ga-0-1",
				"alg": "ga",
				"fitness": "sphere"
			},
			{
				"_id": "5cda2c2826aad517ddea5b75",
				"expId": 1557802012993,
				"iteration": 102,
				"best": 0,
				"bestId": "ga-0-1",
				"alg": "ga",
				"fitness": "sphere"
			},
			{
				"_id": "5cda2c2826aad517ddea5b76",
				"expId": 1557802012993,
				"iteration": 104,
				"best": 0,
				"bestId": "ga-0-1",
				"alg": "ga",
				"fitness": "sphere"
			},
			{
				"_id": "5cda2c2826aad517ddea5b77",
				"expId": 1557802012993,
				"iteration": 106,
				"best": 0,
				"bestId": "ga-0-1",
				"alg": "ga",
				"fitness": "sphere"
			},
			{
				"_id": "5cda2c2826aad517ddea5b78",
				"expId": 1557802012993,
				"iteration": 108,
				"best": 0,
				"bestId": "ga-0-1",
				"alg": "ga",
				"fitness": "sphere"
			},
			{
				"_id": "5cda2c2926aad517ddea5b79",
				"expId": 1557802012993,
				"iteration": 110,
				"best": 0,
				"bestId": "ga-0-1",
				"alg": "ga",
				"fitness": "sphere"
			},
			{
				"_id": "5cda2c2926aad517ddea5b7a",
				"expId": 1557802012993,
				"iteration": 112,
				"best": 0,
				"bestId": "ga-0-1",
				"alg": "ga",
				"fitness": "sphere"
			},
			{
				"_id": "5cda2c2926aad517ddea5b7b",
				"expId": 1557802012993,
				"iteration": 114,
				"best": 0,
				"bestId": "ga-0-1",
				"alg": "ga",
				"fitness": "sphere"
			},
			{
				"_id": "5cda2c2926aad517ddea5b7c",
				"expId": 1557802012993,
				"iteration": 116,
				"best": 0,
				"bestId": "ga-0-1",
				"alg": "ga",
				"fitness": "sphere"
			},
			{
				"_id": "5cda2c2926aad517ddea5b7d",
				"expId": 1557802012993,
				"iteration": 118,
				"best": 0,
				"bestId": "ga-0-1",
				"alg": "ga",
				"fitness": "sphere"
			},
			{
				"_id": "5cda2c2926aad517ddea5b7e",
				"expId": 1557802012993,
				"iteration": 120,
				"best": 0,
				"bestId": "ga-0-1",
				"alg": "ga",
				"fitness": "sphere"
			},
			{
				"_id": "5cda2c2a26aad517ddea5b7f",
				"expId": 1557802012993,
				"iteration": 122,
				"best": 0,
				"bestId": "ga-0-1",
				"alg": "ga",
				"fitness": "sphere"
			},
			{
				"_id": "5cda2c2a26aad517ddea5b80",
				"expId": 1557802012993,
				"iteration": 124,
				"best": 0,
				"bestId": "ga-0-1",
				"alg": "ga",
				"fitness": "sphere"
			},
			{
				"_id": "5cda2c2a26aad517ddea5b81",
				"expId": 1557802012993,
				"iteration": 126,
				"best": 0,
				"bestId": "ga-0-1",
				"alg": "ga",
				"fitness": "sphere"
			},
			{
				"_id": "5cda2c2a26aad517ddea5b83",
				"expId": 1557802012993,
				"iteration": 130,
				"best": 0,
				"bestId": "ga-0-1",
				"alg": "ga",
				"fitness": "sphere"
			},
			{
				"_id": "5cda2c2a26aad517ddea5b82",
				"expId": 1557802012993,
				"iteration": 130,
				"best": 0,
				"bestId": "ga-0-1",
				"alg": "ga",
				"fitness": "sphere"
			},
			{
				"_id": "5cda2c2a26aad517ddea5b84",
				"expId": 1557802012993,
				"iteration": 132,
				"best": 0,
				"bestId": "ga-0-1",
				"alg": "ga",
				"fitness": "sphere"
			},
			{
				"_id": "5cda2c2a26aad517ddea5b85",
				"expId": 1557802012993,
				"iteration": 134,
				"best": 0,
				"bestId": "ga-0-1",
				"alg": "ga",
				"fitness": "sphere"
			},
			{
				"_id": "5cda2c2a26aad517ddea5b86",
				"expId": 1557802012993,
				"iteration": 136,
				"best": 0,
				"bestId": "ga-0-1",
				"alg": "ga",
				"fitness": "sphere"
			},
			{
				"_id": "5cda2c2a26aad517ddea5b87",
				"expId": 1557802012993,
				"iteration": 140,
				"best": 0,
				"bestId": "ga-0-1",
				"alg": "ga",
				"fitness": "sphere"
			},
			{
				"_id": "5cda2c2a26aad517ddea5b88",
				"expId": 1557802012993,
				"iteration": 140,
				"best": 0,
				"bestId": "ga-0-1",
				"alg": "ga",
				"fitness": "sphere"
			},
			{
				"_id": "5cda2c2a26aad517ddea5b89",
				"expId": 1557802012993,
				"iteration": 142,
				"best": 0,
				"bestId": "ga-0-1",
				"alg": "ga",
				"fitness": "sphere"
			},
			{
				"_id": "5cda2c2a26aad517ddea5b8a",
				"expId": 1557802012993,
				"iteration": 144,
				"best": 0,
				"bestId": "ga-0-1",
				"alg": "ga",
				"fitness": "sphere"
			},
			{
				"_id": "5cda2c2b26aad517ddea5b8b",
				"expId": 1557802012993,
				"iteration": 146,
				"best": 0,
				"bestId": "ga-0-1",
				"alg": "ga",
				"fitness": "sphere"
			},
			{
				"_id": "5cda2c2b26aad517ddea5b8c",
				"expId": 1557802012993,
				"iteration": 148,
				"best": 0,
				"bestId": "ga-0-1",
				"alg": "ga",
				"fitness": "sphere"
			},
			{
				"_id": "5cda2c2b26aad517ddea5b8d",
				"expId": 1557802012993,
				"iteration": 150,
				"best": 0,
				"bestId": "ga-0-1",
				"alg": "ga",
				"fitness": "sphere"
			},
			{
				"_id": "5cda2c2b26aad517ddea5b8e",
				"expId": 1557802012993,
				"iteration": 152,
				"best": 0,
				"bestId": "ga-0-1",
				"alg": "ga",
				"fitness": "sphere"
			},
			{
				"_id": "5cda2c2b26aad517ddea5b8f",
				"expId": 1557802012993,
				"iteration": 156,
				"best": 0,
				"bestId": "ga-0-1",
				"alg": "ga",
				"fitness": "sphere"
			},
			{
				"_id": "5cda2c2b26aad517ddea5b90",
				"expId": 1557802012993,
				"iteration": 156,
				"best": 0,
				"bestId": "ga-0-1",
				"alg": "ga",
				"fitness": "sphere"
			},
			{
				"_id": "5cda2c2b26aad517ddea5b91",
				"expId": 1557802012993,
				"iteration": 158,
				"best": 0,
				"bestId": "ga-0-1",
				"alg": "ga",
				"fitness": "sphere"
			},
			{
				"_id": "5cda2c2b26aad517ddea5b92",
				"expId": 1557802012993,
				"iteration": 160,
				"best": 0,
				"bestId": "ga-0-1",
				"alg": "ga",
				"fitness": "sphere"
			},
			{
				"_id": "5cda2c2b26aad517ddea5b93",
				"expId": 1557802012993,
				"iteration": 162,
				"best": 0,
				"bestId": "ga-0-1",
				"alg": "ga",
				"fitness": "sphere"
			},
			{
				"_id": "5cda2c2b26aad517ddea5b94",
				"expId": 1557802012993,
				"iteration": 164,
				"best": 0,
				"bestId": "ga-0-1",
				"alg": "ga",
				"fitness": "sphere"
			},
			{
				"_id": "5cda2c2b26aad517ddea5b95",
				"expId": 1557802012993,
				"iteration": 166,
				"best": 0,
				"bestId": "ga-0-1",
				"alg": "ga",
				"fitness": "sphere"
			},
			{
				"_id": "5cda2c2b26aad517ddea5b96",
				"expId": 1557802012993,
				"iteration": 168,
				"best": 0,
				"bestId": "ga-0-1",
				"alg": "ga",
				"fitness": "sphere"
			},
			{
				"_id": "5cda2c2c26aad517ddea5b97",
				"expId": 1557802012993,
				"iteration": 170,
				"best": 0,
				"bestId": "ga-0-1",
				"alg": "ga",
				"fitness": "sphere"
			},
			{
				"_id": "5cda2c2d26aad517ddea5b98",
				"expId": 1557802012993,
				"iteration": 172,
				"best": 0,
				"bestId": "ga-0-1",
				"alg": "ga",
				"fitness": "sphere"
			},
			{
				"_id": "5cda2c2d26aad517ddea5b99",
				"expId": 1557802012993,
				"iteration": 174,
				"best": 0,
				"bestId": "ga-0-1",
				"alg": "ga",
				"fitness": "sphere"
			},
			{
				"_id": "5cda2c2d26aad517ddea5b9a",
				"expId": 1557802012993,
				"iteration": 176,
				"best": 0,
				"bestId": "ga-0-1",
				"alg": "ga",
				"fitness": "sphere"
			},
			{
				"_id": "5cda2c2d26aad517ddea5b9b",
				"expId": 1557802012993,
				"iteration": 178,
				"best": 0,
				"bestId": "ga-0-1",
				"alg": "ga",
				"fitness": "sphere"
			},
			{
				"_id": "5cda2c2d26aad517ddea5b9c",
				"expId": 1557802012993,
				"iteration": 180,
				"best": 0,
				"bestId": "ga-0-1",
				"alg": "ga",
				"fitness": "sphere"
			},
			{
				"_id": "5cda2c2d26aad517ddea5b9d",
				"expId": 1557802012993,
				"iteration": 182,
				"best": 0,
				"bestId": "ga-0-1",
				"alg": "ga",
				"fitness": "sphere"
			},
			{
				"_id": "5cda2c2d26aad517ddea5b9e",
				"expId": 1557802012993,
				"iteration": 184,
				"best": 0,
				"bestId": "ga-0-1",
				"alg": "ga",
				"fitness": "sphere"
			},
			{
				"_id": "5cda2c2d26aad517ddea5b9f",
				"expId": 1557802012993,
				"iteration": 186,
				"best": 0,
				"bestId": "ga-0-1",
				"alg": "ga",
				"fitness": "sphere"
			},
			{
				"_id": "5cda2c2e26aad517ddea5ba0",
				"expId": 1557802012993,
				"iteration": 188,
				"best": 0,
				"bestId": "ga-0-1",
				"alg": "ga",
				"fitness": "sphere"
			},
			{
				"_id": "5cda2c2e26aad517ddea5ba1",
				"expId": 1557802012993,
				"iteration": 190,
				"best": 0,
				"bestId": "ga-0-1",
				"alg": "ga",
				"fitness": "sphere"
			},
			{
				"_id": "5cda2c2e26aad517ddea5ba2",
				"expId": 1557802012993,
				"iteration": 192,
				"best": 0,
				"bestId": "ga-0-1",
				"alg": "ga",
				"fitness": "sphere"
			},
			{
				"_id": "5cda2c2e26aad517ddea5ba3",
				"expId": 1557802012993,
				"iteration": 194,
				"best": 0,
				"bestId": "ga-0-1",
				"alg": "ga",
				"fitness": "sphere"
			},
			{
				"_id": "5cda2c2e26aad517ddea5ba4",
				"expId": 1557802012993,
				"iteration": 196,
				"best": 0,
				"bestId": "ga-0-1",
				"alg": "ga",
				"fitness": "sphere"
			},
			{
				"_id": "5cda2c2e26aad517ddea5ba5",
				"expId": 1557802012993,
				"iteration": 198,
				"best": 0,
				"bestId": "ga-0-1",
				"alg": "ga",
				"fitness": "sphere"
			},
			{
				"_id": "5cda2c2e26aad517ddea5ba6",
				"expId": 1557802012993,
				"iteration": 200,
				"best": 0,
				"bestId": "ga-0-1",
				"alg": "ga",
				"fitness": "sphere"
			},
			{
				"_id": "5cda2c2e26aad517ddea5ba7",
				"expId": 1557802012993,
				"iteration": 202,
				"best": 0,
				"bestId": "ga-0-1",
				"alg": "ga",
				"fitness": "sphere"
			}
		],
		"rastrigin": []
	}
}
